{
    "FNN_small": {
        "0.05": {
            "50": {
                "drawdown": 0.30899999999999994,
                "rs": 1.0,
                "gene": 0.444,
                "time": 35.859122385270894
            },
            "100": {
                "drawdown": 0.2579,
                "rs": 1.0,
                "gene": 0.487,
                "time": 80.79421643400565
            },
            "200": {
                "drawdown": 0.39549999999999996,
                "rs": 1.0,
                "gene": 0.4265,
                "time": 268.2413650029339
            },
            "500": {
                "drawdown": 0.5609999999999999,
                "rs": 1.0,
                "gene": 0.39,
                "time": 1358.402753755916
            },
            "1000": {
                "drawdown": 0.4313,
                "rs": 1.0,
                "gene": 0.4127,
                "time": 3473.4972438761033
            }
        },
        "0.1": {
            "50": {
                "drawdown": 0.7134,
                "rs": 1.0,
                "gene": 0.242,
                "time": 51.63099597301334
            },
            "100": {
                "drawdown": 0.6243,
                "rs": 1.0,
                "gene": 0.298,
                "time": 92.22594993608072
            },
            "200": {
                "drawdown": 0.6009,
                "rs": 1.0,
                "gene": 0.327,
                "time": 321.8022695952095
            },
            "500": {
                "drawdown": 0.5164,
                "rs": 1.0,
                "gene": 0.375,
                "time": 1324.5789405377582
            },
            "1000": {
                "drawdown": 0.4245,
                "rs": 1.0,
                "gene": 0.4247,
                "time": 3844.8436209568754
            }
        },
        "0.3": {
            "50": {
                "drawdown": 0.7695,
                "rs": 1.0,
                "gene": 0.242,
                "time": 55.34481777017936
            },
            "100": {
                "drawdown": 0.7409,
                "rs": 1.0,
                "gene": 0.22,
                "time": 115.67261543124914
            },
            "200": {
                "drawdown": 0.6282,
                "rs": 1.0,
                "gene": 0.2605,
                "time": 364.940625092946
            },
            "500": {
                "drawdown": 0.5708,
                "rs": 1.0,
                "gene": 0.3044,
                "time": 1934.3855864251964
            },
            "1000": {
                "drawdown": 0.5828,
                "rs": 1.0,
                "gene": 0.3188,
                "time": 3759.560415907763
            }
        }
    },
    "FNN_big": {
        "0.05": {
            "50": {
                "drawdown": 0.006900000000000017,
                "rs": 1.0,
                "gene": 0.63,
                "time": 89.45417244825512
            },
            "100": {
                "drawdown": 0.008099999999999996,
                "rs": 1.0,
                "gene": 0.633,
                "time": 171.08999794116244
            },
            "200": {
                "drawdown": 0.009800000000000031,
                "rs": 1.0,
                "gene": 0.589,
                "time": 418.9705732371658
            },
            "500": {
                "drawdown": 0.01639999999999997,
                "rs": 1.0,
                "gene": 0.5482,
                "time": 1390.057190001011
            },
            "1000": {
                "drawdown": 0.019399999999999973,
                "rs": 1.0,
                "gene": 0.5463,
                "time": 4138.963314766996
            }
        },
        "0.1": {
            "50": {
                "drawdown": 0.06699999999999995,
                "rs": 1.0,
                "gene": 0.526,
                "time": 88.23531418479979
            },
            "100": {
                "drawdown": 0.05620000000000003,
                "rs": 1.0,
                "gene": 0.475,
                "time": 173.65293512912467
            },
            "200": {
                "drawdown": 0.06120000000000003,
                "rs": 1.0,
                "gene": 0.4965,
                "time": 445.45184697117656
            },
            "500": {
                "drawdown": 0.07409999999999994,
                "rs": 1.0,
                "gene": 0.5062,
                "time": 1403.5641998988576
            },
            "1000": {
                "drawdown": 0.08340000000000003,
                "rs": 1.0,
                "gene": 0.511,
                "time": 4321.592856978998
            }
        },
        "0.3": {
            "50": {
                "drawdown": 0.275,
                "rs": 1.0,
                "gene": 0.422,
                "time": 119.45003092568368
            },
            "100": {
                "drawdown": 0.3176,
                "rs": 1.0,
                "gene": 0.434,
                "time": 253.1238534920849
            },
            "200": {
                "drawdown": 0.2853,
                "rs": 1.0,
                "gene": 0.4075,
                "time": 630.4639221583493
            },
            "500": {
                "drawdown": 0.23860000000000003,
                "rs": 1.0,
                "gene": 0.3686,
                "time": 2117.7416542829014
            },
            "1000": {
                "drawdown": 0.23609999999999998,
                "rs": 1.0,
                "gene": 0.365,
                "time": 5480.271931280848
            }
        }
    },
    "CNN_small": {
        "0.05": {
            "50": {
                "drawdown": 0.008299999999999974,
                "rs": 1.0,
                "gene": 0.696,
                "time": 6.1833257442340255
            },
            "100": {
                "drawdown": 0.007400000000000073,
                "rs": 1.0,
                "gene": 0.745,
                "time": 5.128505717031658
            },
            "200": {
                "drawdown": 0.009500000000000064,
                "rs": 1.0,
                "gene": 0.798,
                "time": 18.96322164963931
            },
            "500": {
                "drawdown": 0.011700000000000044,
                "rs": 1.0,
                "gene": 0.8896,
                "time": 146.22363455127925
            },
            "1000": {
                "drawdown": 0.017800000000000038,
                "rs": 1.0,
                "gene": 0.9223,
                "time": 549.094460405875
            }
        },
        "0.1": {
            "50": {
                "drawdown": 0.010099999999999998,
                "rs": 1.0,
                "gene": 0.53,
                "time": 45.60637692315504
            },
            "100": {
                "drawdown": 0.010299999999999976,
                "rs": 1.0,
                "gene": 0.691,
                "time": 9.807721860706806
            },
            "200": {
                "drawdown": 0.022199999999999998,
                "rs": 1.0,
                "gene": 0.7325,
                "time": 41.05836691102013
            },
            "500": {
                "drawdown": 0.017000000000000015,
                "rs": 1.0,
                "gene": 0.845,
                "time": 139.1762151871808
            },
            "1000": {
                "drawdown": 0.023600000000000065,
                "rs": 1.0,
                "gene": 0.9029,
                "time": 492.71883243508637
            }
        },
        "0.3": {
            "50": {
                "drawdown": 0.43220000000000003,
                "rs": 1.0,
                "gene": 0.448,
                "time": 3.758421461097896
            },
            "100": {
                "drawdown": 0.3882,
                "rs": 1.0,
                "gene": 0.599,
                "time": 29.416615654714406
            },
            "200": {
                "drawdown": 0.36819999999999997,
                "rs": 1.0,
                "gene": 0.694,
                "time": 59.94476699503139
            },
            "500": {
                "drawdown": 0.48800000000000004,
                "rs": 1.0,
                "gene": 0.796,
                "time": 167.93645454430953
            },
            "1000": {
                "drawdown": 0.565,
                "rs": 1.0,
                "gene": 0.8585,
                "time": 423.7711988748051
            }
        }
    }
}